mendeley2/__init__.py
mendeley2/auth.py
mendeley2/exception.py
mendeley2/models.py
mendeley2/pagination.py
mendeley2/response.py
mendeley2/session.py
mendeley2/version.py
mendeley2/models/__init__.py
mendeley2/models/annotations.py
mendeley2/models/base_documents.py
mendeley2/models/catalog.py
mendeley2/models/common.py
mendeley2/models/documents.py
mendeley2/models/files.py
mendeley2/models/groups.py
mendeley2/models/profiles.py
mendeley2/resources/__init__.py
mendeley2/resources/annotations.py
mendeley2/resources/base.py
mendeley2/resources/base_documents.py
mendeley2/resources/catalog.py
mendeley2/resources/documents.py
mendeley2/resources/files.py
mendeley2/resources/groups.py
mendeley2/resources/profiles.py
mendeley2/resources/trash.py
mendeley2-0.3.4.dist-info/LICENSE
mendeley2-0.3.4.dist-info/METADATA
mendeley2-0.3.4.dist-info/WHEEL
mendeley2-0.3.4.dist-info/top_level.txt
mendeley2-0.3.4.dist-info/RECORD
